django_keychain/__init__.py
django_keychain-0.0.1.dist-info/METADATA
django_keychain-0.0.1.dist-info/RECORD
django_keychain-0.0.1.dist-info/WHEEL
django_keychain-0.0.1.dist-info/top_level.txt
