Metadata-Version: 2.1
Name: django-keychain
Version: 0.0.1
Summary: Django Keychain
Home-page: UNKNOWN
Author: Gregory Reshetniak
Author-email: ror6ax@gmail.com
License: UNKNOWN
Platform: UNKNOWN
Requires-Dist: boto3
